pautobot/__init__.py
pautobot/app.py
pautobot/app_info.py
pautobot/config.py
pautobot/database.py
pautobot/db_models.py
pautobot/globals.py
pautobot/models.py
pautobot/utils.py
pautobot/engine/__init__.py
pautobot/engine/bot_context.py
pautobot/engine/bot_enums.py
pautobot/engine/chatbot_factory.py
pautobot/engine/context_manager.py
pautobot/engine/engine.py
pautobot/engine/ingest.py
pautobot/engine/llm_factory.py
pautobot/engine/qa_factory.py
pautobot/frontend-dist/404.html
pautobot/frontend-dist/favicon.ico
pautobot/frontend-dist/index.html
pautobot/frontend-dist/loading.svg
pautobot/frontend-dist/pautobot.png
pautobot/frontend-dist/_next/static/O6NpxNnUx3EJw20Dp4g6V/_buildManifest.js
pautobot/frontend-dist/_next/static/O6NpxNnUx3EJw20Dp4g6V/_ssgManifest.js
pautobot/frontend-dist/_next/static/chunks/framework-2c79e2a64abdb08b.js
pautobot/frontend-dist/_next/static/chunks/main-7c8966651ff4862e.js
pautobot/frontend-dist/_next/static/chunks/polyfills-c67a75d1b6f99dc8.js
pautobot/frontend-dist/_next/static/chunks/webpack-8fa1640cc84ba8fe.js
pautobot/frontend-dist/_next/static/chunks/pages/_app-aa96ce9bb1e646b0.js
pautobot/frontend-dist/_next/static/chunks/pages/_error-54de1933a164a1ff.js
pautobot/frontend-dist/_next/static/chunks/pages/index-994b581788040fa9.js
pautobot/frontend-dist/_next/static/css/9b042cfeba8e2c71.css
pautobot/frontend-dist/_next/static/media/037c6ceced78c87a-s.woff2
pautobot/frontend-dist/_next/static/media/03a2ebda46411260-s.woff2
pautobot/frontend-dist/_next/static/media/2cffe11a47028c14-s.woff2
pautobot/frontend-dist/_next/static/media/4ab03c045edad786-s.p.woff2
pautobot/frontend-dist/_next/static/media/4cf1eda6528c4545-s.p.woff2
pautobot/frontend-dist/_next/static/media/51fbb2aa5ef2b5cf-s.woff2
pautobot/frontend-dist/_next/static/media/560bcc4e09749527-s.woff2
pautobot/frontend-dist/_next/static/media/6cb9e821df97febd-s.p.woff2
pautobot/frontend-dist/_next/static/media/723f3c07bb1fbaab-s.woff2
pautobot-0.0.27.dist-info/METADATA
pautobot-0.0.27.dist-info/WHEEL
pautobot-0.0.27.dist-info/entry_points.txt
pautobot-0.0.27.dist-info/top_level.txt
pautobot-0.0.27.dist-info/RECORD
